DeepQ/__init__.py
DeepQ-0.0.3.dist-info/LICENSE
DeepQ-0.0.3.dist-info/METADATA
DeepQ-0.0.3.dist-info/WHEEL
DeepQ-0.0.3.dist-info/top_level.txt
DeepQ-0.0.3.dist-info/RECORD
